hashcracker/__init__.py
hashcracker/crdt.py
hashcracker/hashcracker.py
hashcracker-0.0.1b0.dist-info/LICENSE
hashcracker-0.0.1b0.dist-info/METADATA
hashcracker-0.0.1b0.dist-info/WHEEL
hashcracker-0.0.1b0.dist-info/entry_points.txt
hashcracker-0.0.1b0.dist-info/top_level.txt
hashcracker-0.0.1b0.dist-info/RECORD
